oldcode/__init__.py
oldcode/find_scars.py
oldcode/code/__init__.py
oldcode/code/compress_mpileup.py
oldcode/code/count_remaining.py
oldcode/code/genetic_code.py
oldcode/code/get_scar_indels.py
oldcode/code/globalvars.py
oldcode/code/qcmap.py
oldcode/code/scars_functions.py
oldcode/code/strain_distances.py
scartrek/__init__.py
scartrek/find_scars.py
scartrek/functions_genic_mutations.py
scartrek/genetic_code.py
scartrek/genic_mutations.py
scartrek/globalvars.py
scartrek/scars_functions.py
utils/__init__.py
scartrek-1.0.0.dist-info/LICENSE.txt
scartrek-1.0.0.dist-info/METADATA
scartrek-1.0.0.dist-info/WHEEL
scartrek-1.0.0.dist-info/entry_points.txt
scartrek-1.0.0.dist-info/top_level.txt
scartrek-1.0.0.dist-info/RECORD
