Metadata-Version: 2.1
Name: scartrek
Version: 1.0.0
Summary: Python package for identifying gene disrupting and restoring indels in whole-genome sequencing data of Mycobacterium tuberculosis samples
Home-page: https://github.com/aditi9783/ScarTrek
Author: Aditi Gupta
Author-email: aditi9783@gmail.com
License: UNKNOWN
Platform: UNKNOWN
Classifier: Programming Language :: Python :: 2
Classifier: License :: OSI Approved :: MIT License
Classifier: Operating System :: OS Independent
Requires-Python: >=2.7
